aurimyth/foundation_kit/__init__.py
aurimyth/foundation_kit/_version.py
aurimyth/foundation_kit/application/__init__.py
aurimyth/foundation_kit/application/app/__init__.py
aurimyth/foundation_kit/application/app/base.py
aurimyth/foundation_kit/application/app/components.py
aurimyth/foundation_kit/application/app/middlewares.py
aurimyth/foundation_kit/application/config/__init__.py
aurimyth/foundation_kit/application/config/settings.py
aurimyth/foundation_kit/application/constants/__init__.py
aurimyth/foundation_kit/application/constants/components.py
aurimyth/foundation_kit/application/constants/scheduler.py
aurimyth/foundation_kit/application/constants/service.py
aurimyth/foundation_kit/application/errors/__init__.py
aurimyth/foundation_kit/application/errors/chain.py
aurimyth/foundation_kit/application/errors/codes.py
aurimyth/foundation_kit/application/errors/exceptions.py
aurimyth/foundation_kit/application/errors/handlers.py
aurimyth/foundation_kit/application/errors/response.py
aurimyth/foundation_kit/application/interfaces/__init__.py
aurimyth/foundation_kit/application/interfaces/egress.py
aurimyth/foundation_kit/application/interfaces/ingress.py
aurimyth/foundation_kit/application/middleware/__init__.py
aurimyth/foundation_kit/application/middleware/logging.py
aurimyth/foundation_kit/application/migrations/__init__.py
aurimyth/foundation_kit/application/migrations/manager.py
aurimyth/foundation_kit/application/migrations/setup.py
aurimyth/foundation_kit/application/rpc/__init__.py
aurimyth/foundation_kit/application/rpc/base.py
aurimyth/foundation_kit/application/rpc/client.py
aurimyth/foundation_kit/application/rpc/discovery.py
aurimyth/foundation_kit/application/scheduler/__init__.py
aurimyth/foundation_kit/application/scheduler/runner.py
aurimyth/foundation_kit/application/server/__init__.py
aurimyth/foundation_kit/commands/__init__.py
aurimyth/foundation_kit/commands/add.py
aurimyth/foundation_kit/commands/app.py
aurimyth_foundation_kit-0.0.6.dist-info/METADATA
aurimyth_foundation_kit-0.0.6.dist-info/WHEEL
aurimyth_foundation_kit-0.0.6.dist-info/entry_points.txt
aurimyth_foundation_kit-0.0.6.dist-info/RECORD
