Metadata-Version: 2.4
Name: aurimyth-foundation-kit
Version: 0.0.6
Summary: AuriMyth Foundation Kit - 核心基础架构工具包
Requires-Python: >=3.13
Requires-Dist: alembic>=1.17.2
Requires-Dist: babel>=2.17.0
Requires-Dist: faker>=38.2.0
Requires-Dist: fastapi>=0.122.0
Requires-Dist: greenlet>=3.2.4
Requires-Dist: httpx>=0.28.1
Requires-Dist: loguru>=0.7.3
Requires-Dist: pydantic-settings>=2.12.0
Requires-Dist: pydantic>=2.12.5
Requires-Dist: rich>=14.2.0
Requires-Dist: sqlalchemy>=2.0.44
Requires-Dist: tenacity>=9.1.2
Requires-Dist: typer>=0.20.0
Requires-Dist: uvicorn[standard]>=0.30.0
Provides-Extra: admin
Requires-Dist: itsdangerous>=2.2.0; extra == 'admin'
Requires-Dist: sqladmin>=0.16.0; extra == 'admin'
Provides-Extra: all
Requires-Dist: aiomysql>=0.3.2; extra == 'all'
Requires-Dist: aiosqlite>=0.21.0; extra == 'all'
Requires-Dist: amqp>=5.3.1; extra == 'all'
Requires-Dist: apscheduler>=3.11.1; extra == 'all'
Requires-Dist: asyncpg>=0.31.0; extra == 'all'
Requires-Dist: aurimyth-storage-sdk[aws]>=0.0.1; extra == 'all'
Requires-Dist: dramatiq-kombu-broker>=0.2.2; extra == 'all'
Requires-Dist: dramatiq>=1.18.0; extra == 'all'
Requires-Dist: kombu>=5.6.1; extra == 'all'
Requires-Dist: redis>=7.1.0; extra == 'all'
Provides-Extra: dev
Requires-Dist: mypy>=1.19.0; extra == 'dev'
Requires-Dist: pytest-asyncio>=1.3.0; extra == 'dev'
Requires-Dist: pytest-cov>=7.0.0; extra == 'dev'
Requires-Dist: pytest>=9.0.1; extra == 'dev'
Requires-Dist: ruff>=0.14.7; extra == 'dev'
Provides-Extra: docs
Requires-Dist: materialx>=1.39.0; extra == 'docs'
Requires-Dist: mkdocs-material>=9.7.0; extra == 'docs'
Requires-Dist: mkdocs>=1.6.0; extra == 'docs'
Provides-Extra: mysql
Requires-Dist: aiomysql>=0.3.2; extra == 'mysql'
Provides-Extra: postgres
Requires-Dist: asyncpg>=0.31.0; extra == 'postgres'
Provides-Extra: rabbitmq
Requires-Dist: amqp>=5.3.1; extra == 'rabbitmq'
Provides-Extra: recommended
Requires-Dist: apscheduler>=3.11.1; extra == 'recommended'
Requires-Dist: asyncpg>=0.31.0; extra == 'recommended'
Requires-Dist: aurimyth-storage-sdk[aws]>=0.0.1; extra == 'recommended'
Requires-Dist: dramatiq-kombu-broker>=0.2.2; extra == 'recommended'
Requires-Dist: dramatiq>=1.18.0; extra == 'recommended'
Requires-Dist: kombu>=5.6.1; extra == 'recommended'
Requires-Dist: redis>=7.1.0; extra == 'recommended'
Provides-Extra: redis
Requires-Dist: redis>=7.1.0; extra == 'redis'
Provides-Extra: s3
Requires-Dist: aurimyth-storage-sdk[aws]>=0.0.1; extra == 's3'
Provides-Extra: scheduler
Requires-Dist: apscheduler>=3.11.1; extra == 'scheduler'
Provides-Extra: sqlite
Requires-Dist: aiosqlite>=0.21.0; extra == 'sqlite'
Provides-Extra: tasks
Requires-Dist: dramatiq-kombu-broker>=0.2.2; extra == 'tasks'
Requires-Dist: dramatiq>=1.18.0; extra == 'tasks'
Requires-Dist: kombu>=5.6.1; extra == 'tasks'
